includes/2_scan.py
includes/__init__.py
includes/message.py
includes/payload_url.py
includes/read_file.py
includes/scan.py
includes/sms_id.py
includes/write_output.py
utils/__init__.py
utils/banner.py
utils/check_internet.py
OpenRedirectVulnerablityScanner-0.0.3.dist-info/METADATA
OpenRedirectVulnerablityScanner-0.0.3.dist-info/WHEEL
OpenRedirectVulnerablityScanner-0.0.3.dist-info/entry_points.txt
OpenRedirectVulnerablityScanner-0.0.3.dist-info/top_level.txt
OpenRedirectVulnerablityScanner-0.0.3.dist-info/RECORD
