Metadata-Version: 2.1
Name: OpenRedirectVulnerablityScanner
Version: 0.0.3
Summary: Open Redirect Vulnerability Scanner for Bug Bounty Hunters
Author: Nawin
Author-email: vnawin8@gmail.com
Classifier: Development Status :: 1 - Planning
Classifier: Intended Audience :: Developers
Classifier: Programming Language :: Python :: 3
Classifier: Operating System :: Unix
Classifier: Operating System :: MacOS
Classifier: Operating System :: Microsoft :: Windows
Requires-Python: >=3.6
Requires-Dist: requests
Requires-Dist: twilio
Requires-Dist: urllib3
